balrog/__init__.py
balrog/exceptions.py
balrog/permission.py
balrog/policy.py
balrog/role.py
balrog-1.1.0.dist-info/LICENSE.txt
balrog-1.1.0.dist-info/METADATA
balrog-1.1.0.dist-info/WHEEL
balrog-1.1.0.dist-info/top_level.txt
balrog-1.1.0.dist-info/RECORD
